[{"model": "portal.waitlist", "pk": 4, "fields": {"building": "Tulsi", "applicant": []}}, {"model": "portal.waitlist", "pk": 5, "fields": {"building": "Manas", "applicant": []}}, {"model": "portal.waitlist", "pk": 6, "fields": {"building": "Type-1", "applicant": []}}, {"model": "portal.occupiedlist", "pk": 1, "fields": {"building": "Type-1", "applicant": []}}, {"model": "portal.occupiedlist", "pk": 2, "fields": {"building": "Tulsi", "applicant": []}}, {"model": "portal.occupiedlist", "pk": 3, "fields": {"building": "Manas", "applicant": []}}, {"model": "portal.vacatedlist", "pk": 1, "fields": {"building": "Type-1", "applicant": []}}, {"model": "portal.vacatedlist", "pk": 2, "fields": {"building": "Tulsi", "applicant": []}}, {"model": "portal.vacatedlist", "pk": 3, "fields": {"building": "Manas", "applicant": []}}]